myfitbit/__init__.py
myfitbit/__main__.py
myfitbit/_version.py
myfitbit/auth.py
myfitbit/client.py
myfitbit/datastore.py
myfitbit/report.py
myfitbit/sync.py
myfitbit/static/chart.js
myfitbit/static/report.css
myfitbit-0.7.0.dist-info/METADATA
myfitbit-0.7.0.dist-info/RECORD
myfitbit-0.7.0.dist-info/WHEEL
myfitbit-0.7.0.dist-info/top_level.txt
